lifty/__init__.py
lifty/elevator.py
lifty/status.py
tests/__init__.py
tests/test_elevator.py
lifty-0.0.3.dist-info/LICENSE
lifty-0.0.3.dist-info/METADATA
lifty-0.0.3.dist-info/WHEEL
lifty-0.0.3.dist-info/top_level.txt
lifty-0.0.3.dist-info/zip-safe
lifty-0.0.3.dist-info/RECORD
