Metadata-Version: 2.1
Name: lifty
Version: 0.0.3
Summary: For simulating an elevator in python
Home-page: https://github.com/charlesshook/lifty
Author: Charles Shook
Classifier: Programming Language :: Python :: 3
Classifier: License :: OSI Approved :: MIT License
Classifier: Operating System :: OS Independent
Requires-Python: >=3.9
License-File: LICENSE
